[
    {
        "crates": 3,
        "database_loaded_time": "2.818422404s",
        "declarations": 7097,
        "expressions": 119351,
        "functions": 2762,
        "inferenece_time": "17.875815319s",
        "item_collection_time": "11.499345873s",
        "modules": 213,
        "partial_unknown_types": 3797,
        "project_name": "./rustc-perf/collector/benchmarks/cargo/",
        "roots": 132,
        "total_time": "29.375170692s",
        "type_mismatches": 10908,
        "unknown_types": 4223
    },
    {
        "crates": 63,
        "database_loaded_time": "859.788528ms",
        "declarations": 3545,
        "expressions": 64206,
        "functions": 1272,
        "inferenece_time": "12.114284672s",
        "item_collection_time": "7.458679785s",
        "modules": 115,
        "partial_unknown_types": 2279,
        "project_name": "./rustc-perf/collector/benchmarks/clap-rs/",
        "roots": 77,
        "total_time": "19.573014457s",
        "type_mismatches": 2427,
        "unknown_types": 3248
    },
    {
        "crates": 21,
        "database_loaded_time": "1.5107501s",
        "declarations": 9673,
        "expressions": 150354,
        "functions": 2991,
        "inferenece_time": "19.052674103s",
        "item_collection_time": "7.96385633s",
        "modules": 315,
        "partial_unknown_types": 7192,
        "project_name": "./rustc-perf/collector/benchmarks/cranelift-codegen/",
        "roots": 132,
        "total_time": "27.016540233s",
        "type_mismatches": 6419,
        "unknown_types": 8963
    },
    {
        "crates": 1,
        "database_loaded_time": "392.958445ms",
        "declarations": 1495,
        "expressions": 7333,
        "functions": 257,
        "inferenece_time": "5.435691608s",
        "item_collection_time": "2.392833472s",
        "modules": 55,
        "partial_unknown_types": 1663,
        "project_name": "./rustc-perf/collector/benchmarks/futures/",
        "roots": 16,
        "total_time": "7.82853328s",
        "type_mismatches": 405,
        "unknown_types": 975
    },
    {
        "crates": 1,
        "database_loaded_time": "79.269208ms",
        "declarations": 18,
        "expressions": 5,
        "functions": 1,
        "inferenece_time": "2.248858444s",
        "item_collection_time": "2.317817554s",
        "modules": 1,
        "partial_unknown_types": 0,
        "project_name": "./rustc-perf/collector/benchmarks/helloworld/",
        "roots": 15,
        "total_time": "4.566702498s",
        "type_mismatches": 1,
        "unknown_types": 0
    },
    {
        "crates": 2,
        "database_loaded_time": "3.205199643s",
        "declarations": 845,
        "expressions": 13820,
        "functions": 255,
        "inferenece_time": "6.916883304s",
        "item_collection_time": "5.999770428s",
        "modules": 28,
        "partial_unknown_types": 258,
        "project_name": "./rustc-perf/collector/benchmarks/html5ever/",
        "roots": 56,
        "total_time": "12.916678832s",
        "type_mismatches": 290,
        "unknown_types": 451
    },
    {
        "crates": 1,
        "database_loaded_time": "753.912675ms",
        "declarations": 4097,
        "expressions": 23945,
        "functions": 819,
        "inferenece_time": "6.835484755s",
        "item_collection_time": "5.815498173s",
        "modules": 167,
        "partial_unknown_types": 1581,
        "project_name": "./rustc-perf/collector/benchmarks/hyper/",
        "roots": 51,
        "total_time": "12.651029028s",
        "type_mismatches": 1015,
        "unknown_types": 2189
    },
    {
        "crates": 9,
        "database_loaded_time": "1.165642809s",
        "declarations": 2490,
        "expressions": 20056,
        "functions": 987,
        "inferenece_time": "7.44808467s",
        "item_collection_time": "6.430239296s",
        "modules": 65,
        "partial_unknown_types": 2311,
        "project_name": "./rustc-perf/collector/benchmarks/syn/",
        "roots": 58,
        "total_time": "13.878332666s",
        "type_mismatches": 987,
        "unknown_types": 3975
    }
]